resokit/__init__.py
resokit/_version.py
resokit/core.py
resokit/datasets/__init__.py
resokit/datasets/databases.py
resokit/datasets/utils.py
resokit/load/__init__.py
resokit/load/load.py
resokit/query/__init__.py
resokit/query/query.py
resokit/units/__init__.py
resokit/units/units.py
resokit/utils/__init__.py
resokit/utils/parser.py
resokit/utils/utils.py
resokit/utils/mass_radius/__init__.py
resokit/utils/mass_radius/models.py
resokit/utils/mmr/__init__.py
resokit/utils/mmr/mmrs.py
resokit-1.0.4.dist-info/licenses/LICENSE
resokit-1.0.4.dist-info/METADATA
resokit-1.0.4.dist-info/WHEEL
resokit-1.0.4.dist-info/top_level.txt
resokit-1.0.4.dist-info/RECORD
