Metadata-Version: 2.4
Name: resokit
Version: 1.0.4
Summary: Miscellaneous tools for the analysis of planetary systems.
Author-email: Emmanuel Gianuzzi <egianuzzi@unc.edu.ar>, Matías Cerioni <matias.cerioni@unc.edu.ar>
License: MIT
Project-URL: Homepage, https://github.com/Gianuzzi/resokit
Keywords: resokit,planetary systems,resonances,databases
Classifier: Development Status :: 2 - Pre-Alpha
Classifier: Intended Audience :: Education
Classifier: Intended Audience :: Science/Research
Classifier: License :: OSI Approved :: MIT License
Classifier: Operating System :: OS Independent
Classifier: Programming Language :: Python
Classifier: Programming Language :: Python :: 3.10
Classifier: Programming Language :: Python :: 3.11
Classifier: Programming Language :: Python :: 3.12
Classifier: Programming Language :: Python :: 3.13
Classifier: Topic :: Scientific/Engineering
License-File: LICENSE
Requires-Dist: attrs
Requires-Dist: numpy
Requires-Dist: matplotlib
Requires-Dist: pandas
Requires-Dist: scipy
Requires-Dist: requests
Requires-Dist: beautifulsoup4
Provides-Extra: query
Requires-Dist: astropy; extra == "query"
Provides-Extra: reb
Requires-Dist: rebound; extra == "reb"
Provides-Extra: all
Requires-Dist: astropy; extra == "all"
Requires-Dist: rebound; extra == "all"
Dynamic: license-file
